pytest_freethreaded/__init__.py
pytest_freethreaded/plugin.py
pytest_freethreaded-0.1.0.dist-info/entry_points.txt
pytest_freethreaded-0.1.0.dist-info/LICENSE
pytest_freethreaded-0.1.0.dist-info/WHEEL
pytest_freethreaded-0.1.0.dist-info/METADATA
pytest_freethreaded-0.1.0.dist-info/RECORD
